Metadata-Version: 2.4
Name: canopy-osint
Version: 0.1.0
Summary: An OSINT tool for intelligence gathering and username enumeration
Author-email: Guy Volvoshin <guyvoloshin@gmail.com>
License: MIT
Project-URL: Homepage, https://github.com/guyvolvo/canopy
Project-URL: Repository, https://github.com/guyvolvo/canopy.git
Project-URL: Issues, https://github.com/guyvolvo/canopy/issues
Keywords: osint,intelligence,reconnaissance,username,enumeration
Classifier: Development Status :: 3 - Alpha
Classifier: Intended Audience :: Information Technology
Classifier: License :: OSI Approved :: MIT License
Classifier: Programming Language :: Python :: 3
Classifier: Programming Language :: Python :: 3.7
Classifier: Programming Language :: Python :: 3.8
Classifier: Programming Language :: Python :: 3.9
Classifier: Programming Language :: Python :: 3.10
Classifier: Programming Language :: Python :: 3.11
Classifier: Programming Language :: Python :: 3.12
Classifier: Operating System :: OS Independent
Classifier: Topic :: Security
Requires-Python: >=3.7
License-File: LICENSE
Requires-Dist: requests>=2.32.0
Provides-Extra: dev
Requires-Dist: pytest>=7.0; extra == "dev"
Requires-Dist: black>=23.0; extra == "dev"
Dynamic: license-file
